pyplugin/__init__.py
pyplugin/base.py
pyplugin/decorators.py
pyplugin/exceptions.py
pyplugin/group.py
pyplugin/settings.py
pyplugin/types.py
pyplugin/utils.py
pyplugin-0.4.1.dist-info/licenses/LICENSE
pyplugin-0.4.1.dist-info/METADATA
pyplugin-0.4.1.dist-info/WHEEL
pyplugin-0.4.1.dist-info/top_level.txt
pyplugin-0.4.1.dist-info/RECORD
