Metadata-Version: 2.4
Name: pyplugin
Version: 0.4.1
Author-email: Evyn Machi <evyn.machi@gmail.com>
License: LICENSE
Project-URL: Homepage, https://github.com/pyplugin/pyplugin
Classifier: Programming Language :: Python :: 3
Classifier: Operating System :: OS Independent
Requires-Python: >=3.9
License-File: LICENSE
Provides-Extra: dev
Requires-Dist: pytest>=7.3.1; extra == "dev"
Requires-Dist: hypothesis>=6.82.0; extra == "dev"
Requires-Dist: black>=23.3.0; extra == "dev"
Requires-Dist: coverage>=7.2.7; extra == "dev"
Requires-Dist: pylint>=2.17.5; extra == "dev"
Requires-Dist: Sphinx<7,>=1.6; extra == "dev"
Requires-Dist: sphinx-rtd-theme>=1.2.2; extra == "dev"
Provides-Extra: build
Requires-Dist: build>=0.10.0; extra == "build"
Requires-Dist: twine>=4.0.2; extra == "build"
Dynamic: license-file
